setup.py
random_number_guessing_game/Game.py
random_number_guessing_game/Hints.py
random_number_guessing_game/Number.py
random_number_guessing_game/Utils.py
random_number_guessing_game/__init__.py
random_number_guessing_game.egg-info/PKG-INFO
random_number_guessing_game.egg-info/SOURCES.txt
random_number_guessing_game.egg-info/dependency_links.txt
random_number_guessing_game.egg-info/not-zip-safe
random_number_guessing_game.egg-info/top_level.txt