Metadata-Version: 1.0
Name: random-number-guessing-game
Version: 0.1
Summary: Random number guessing game
Home-page: UNKNOWN
Author: Stefania Mindoiu
Author-email: stefaniadinica@gmail.com
License: UNKNOWN
Platform: UNKNOWN
